{
  "name": "Marc RDWZ",
  "description": "Full Stack Web Dev",
  "image_url": "https://raw.githubusercontent.com/rdwz/my-links/main/avatar.png",
  "links": [
    {
      "title": "Instagram",
      "url": "https://bit.ly/3LaBWc2",
      "icon": "instagram"
    },
    {
      "title": "Twitter",
      "url": "https://twitter.com/redwerkz",
      "icon": "twitter"
    },
    {
      "title": "LinkedIn",
      "url": "https://www.linkedin.com/in/rdwz",
      "icon": "linkedin"
    },
    {
      "title": "GitHub",
      "url": "https://github.com/rdwz",
      "icon": "github"
    }
  ]
}
